{
    "eventName": "ListOrganizationalUnitsForParent",
    "eventSource": "organizations.amazonaws.com",
    "awsService": "Organizations",
    "description": "Lists the organizational units (OUs) in a parent organizational unit or root.",
    "mitreAttackTactics": [
        "TA0007 - Discovery"
    ],
    "mitreAttackTechniques": [
        "T1526 - Cloud Service Discovery"
    ],
    "usedInWild": true,
    "incidents": [
        {
            "description": "When a Zero Day and Access Keys Collide in the Cloud: Responding to the SugarCRM Zero-Day Vulnerability",
            "link": "https://unit42.paloaltonetworks.com/sugarcrm-cloud-incident-black-hat/"
        }
    ],
    "researchLinks": [],
    "securityImplications": "Attackers might use ListOrganizationalUnitsForParent to map the structure of an organization's AWS environment for potential vulnerabilities."
}