{
    "eventName": "GetSMSSandboxAccountStatus",
    "eventSource": "sns.amazonaws.com",
    "awsService": "SNS",
    "description": "Retrieves the SMS sandbox status for the calling AWS account in the target AWS Region.",
    "mitreAttackTactics": [
        "TA0007 - Discovery"
    ],
    "mitreAttackTechniques": [
        "T1580 - Cloud Infrastructure Discovery"
    ],
    "mitreAttackSubTechniques": [],
    "unverifiedMitreAttackTechniques": [
        {
            "technique": "T1087 - Account Discovery",
            "reason": "This API call allows an adversary to determine the SMS sandbox status, which can reveal if an AWS account is still in a test phase or if it's been moved to production, indicating how the account might be used or targeted."
        }
    ],
    "usedInWild": true,
    "incidents": [
        {
            "description": "Tales from the cloud trenches: Using malicious AWS activity to spot phishing campaigns",
            "link": "https://securitylabs.datadoghq.com/articles/tales-from-the-cloud-trenches-aws-activity-to-phishing/"
        }
    ],
    "researchLinks": [
        {
            "description": "NEW PHONE, WHO DIS? HOW CLOUD ENVIRONMENTS ARE EXPLOITED FOR SMISHING CAMPAIGNS",
            "link": "https://permiso.io/blog/s/smishing-attack-on-aws-sms-new-phone-who-dis/"
        }
    ],
    "securityImplications": "Attackers might use GetSMSSandboxAccountStatus to monitor the status of a target's AWS SNS sandbox account for potential usage for smishing.",
    "alerting": [],
    "simulation": [
        {
            "type": "commandLine",
            "value": "aws sns get-sms-sandbox-account-status"
        }
    ],
    "permissions": "https://aws.permissions.cloud/iam/sns#sns-GetSMSSandboxAccountStatus"
}
